odoo/addons/connector_elasticsearch/README.rst
odoo/addons/connector_elasticsearch/__init__.py
odoo/addons/connector_elasticsearch/__manifest__.py
odoo/addons/connector_elasticsearch/components/__init__.py
odoo/addons/connector_elasticsearch/components/adapter.py
odoo/addons/connector_elasticsearch/components/core.py
odoo/addons/connector_elasticsearch/demo/backend_demo.xml
odoo/addons/connector_elasticsearch/i18n/connector_elasticsearch.pot
odoo/addons/connector_elasticsearch/migrations/13.0.2.1.0/post-migrate.py
odoo/addons/connector_elasticsearch/models/__init__.py
odoo/addons/connector_elasticsearch/models/se_backend_elasticsearch.py
odoo/addons/connector_elasticsearch/models/se_index.py
odoo/addons/connector_elasticsearch/readme/CONTRIBUTORS.rst
odoo/addons/connector_elasticsearch/readme/DESCRIPTION.rst
odoo/addons/connector_elasticsearch/readme/HISTORY.rst
odoo/addons/connector_elasticsearch/security/se_backend_elasticsearch.xml
odoo/addons/connector_elasticsearch/static/description/icon.png
odoo/addons/connector_elasticsearch/static/description/index.html
odoo/addons/connector_elasticsearch/tests/__init__.py
odoo/addons/connector_elasticsearch/tests/docker-compose.elasticsearch.example.yml
odoo/addons/connector_elasticsearch/tests/test_connector_elasticsearch.py
odoo/addons/connector_elasticsearch/tests/cassettes/TestConnectorElasticsearch.test_index_adapter.yaml
odoo/addons/connector_elasticsearch/tests/cassettes/TestConnectorElasticsearch.test_index_adapter_delete.yaml
odoo/addons/connector_elasticsearch/tests/cassettes/TestConnectorElasticsearch.test_index_adapter_delete_nonexisting_documents.yaml
odoo/addons/connector_elasticsearch/tests/cassettes/TestConnectorElasticsearch.test_index_adapter_iter.yaml
odoo/addons/connector_elasticsearch/views/se_backend_elasticsearch.xml
odoo/addons/connector_elasticsearch/views/se_menu.xml
odoo14_addon_connector_elasticsearch-14.0.2.6.1.dist-info/METADATA
odoo14_addon_connector_elasticsearch-14.0.2.6.1.dist-info/WHEEL
odoo14_addon_connector_elasticsearch-14.0.2.6.1.dist-info/top_level.txt
odoo14_addon_connector_elasticsearch-14.0.2.6.1.dist-info/RECORD
