Metadata-Version: 2.1
Name: odoo14-addon-connector-elasticsearch
Version: 14.0.2.6.1
Summary: Connector For Elasticsearch Search Engine
Home-page: https://github.com/OCA/search-engine
Author: ACSONE SA/NV, Odoo Community Association (OCA)
Author-email: support@odoo-community.org
License: AGPL-3
Platform: UNKNOWN
Classifier: Programming Language :: Python
Classifier: Framework :: Odoo
Classifier: Framework :: Odoo :: 14.0
Classifier: License :: OSI Approved :: GNU Affero General Public License v3
Requires-Python: >=3.6
Requires-Dist: elasticsearch (<=7.13.4,>=7.0.0)
Requires-Dist: odoo14-addon-component
Requires-Dist: odoo14-addon-connector
Requires-Dist: odoo14-addon-connector-search-engine
Requires-Dist: odoo14-addon-jsonifier
Requires-Dist: odoo14-addon-server-environment
Requires-Dist: odoo (<14.1dev,>=14.0a)
Requires-Dist: requests
